pybaqus/__init__.py
pybaqus/elements.py
pybaqus/faces.py
pybaqus/fil_result.py
pybaqus/model.py
pybaqus/nodes.py
pybaqus/reader.py
pybaqus/step.py
pybaqus-0.2.16.dist-info/METADATA
pybaqus-0.2.16.dist-info/WHEEL
pybaqus-0.2.16.dist-info/licenses/LICENSE
pybaqus-0.2.16.dist-info/RECORD
