Metadata-Version: 2.4
Name: pybaqus
Version: 0.2.16
Summary: A Python library for the visualization and post-processing of Abaqus ASCII result files
Author-email: Cristóbal Tapia Camú <crtapia@gmail.com>
License-File: LICENSE
Requires-Python: >=3.10
Requires-Dist: numpy>=2.1.2
Requires-Dist: pyvista>=0.44.1
Requires-Dist: scipy>=1.14.1
Requires-Dist: tqdm>=4.66.5
Requires-Dist: vtk>=9.3.1
